README.md
setup.py
py_iqoption_api.egg-info/PKG-INFO
py_iqoption_api.egg-info/SOURCES.txt
py_iqoption_api.egg-info/dependency_links.txt
py_iqoption_api.egg-info/not-zip-safe
py_iqoption_api.egg-info/requires.txt
py_iqoption_api.egg-info/top_level.txt
pyiqoptionapi/__init__.py
pyiqoptionapi/api/__init__.py
pyiqoptionapi/api/api.py
pyiqoptionapi/helpers/__init__.py
pyiqoptionapi/helpers/constants.py
pyiqoptionapi/helpers/countries.py
pyiqoptionapi/helpers/country_id.py
pyiqoptionapi/helpers/expiration.py
pyiqoptionapi/helpers/global_value.py
pyiqoptionapi/http/__init__.py
pyiqoptionapi/http/appinit.py
pyiqoptionapi/http/auth.py
pyiqoptionapi/http/billing.py
pyiqoptionapi/http/buyback.py
pyiqoptionapi/http/changebalance.py
pyiqoptionapi/http/events.py
pyiqoptionapi/http/getprofile.py
pyiqoptionapi/http/getregdata.py
pyiqoptionapi/http/login.py
pyiqoptionapi/http/loginv2.py
pyiqoptionapi/http/logout.py
pyiqoptionapi/http/profile.py
pyiqoptionapi/http/register.py
pyiqoptionapi/http/resource.py
pyiqoptionapi/http/token.py
pyiqoptionapi/ws/__init__.py
pyiqoptionapi/ws/client.py
pyiqoptionapi/ws/chanels/__init__.py
pyiqoptionapi/ws/chanels/api_game_betinfo.py
pyiqoptionapi/ws/chanels/api_game_getoptions.py
pyiqoptionapi/ws/chanels/base.py
pyiqoptionapi/ws/chanels/buy_place_order_temp.py
pyiqoptionapi/ws/chanels/buyback.py
pyiqoptionapi/ws/chanels/buyv2.py
pyiqoptionapi/ws/chanels/buyv3.py
pyiqoptionapi/ws/chanels/cancel_order.py
pyiqoptionapi/ws/chanels/candles.py
pyiqoptionapi/ws/chanels/change_auto_margin_call.py
pyiqoptionapi/ws/chanels/change_tpsl.py
pyiqoptionapi/ws/chanels/changebalance.py
pyiqoptionapi/ws/chanels/close_position.py
pyiqoptionapi/ws/chanels/digital_option.py
pyiqoptionapi/ws/chanels/get_available_leverages.py
pyiqoptionapi/ws/chanels/get_balances.py
pyiqoptionapi/ws/chanels/get_deferred_orders.py
pyiqoptionapi/ws/chanels/get_financial_information.py
pyiqoptionapi/ws/chanels/get_order.py
pyiqoptionapi/ws/chanels/get_overnight_fee.py
pyiqoptionapi/ws/chanels/get_positions.py
pyiqoptionapi/ws/chanels/heartbeat.py
pyiqoptionapi/ws/chanels/instruments.py
pyiqoptionapi/ws/chanels/leaderboard.py
pyiqoptionapi/ws/chanels/sell_option.py
pyiqoptionapi/ws/chanels/setactives.py
