Metadata-Version: 1.0
Name: py-iqoption-api
Version: 1.1.100
Summary: Best IQ Option API for python
Home-page: https://github.com/deibsoncarvalho/py-iqoption-api
Author: Deibson Carvalho
Author-email: deibsoncarvalho@gmail.com
License: UNKNOWN
Platform: UNKNOWN
